svg_text2path/__init__.py
svg_text2path/api.py
svg_text2path/config.py
svg_text2path/exceptions.py
svg_text2path/logging.py
svg_text2path/py.typed
svg_text2path/cli/__init__.py
svg_text2path/cli/main.py
svg_text2path/cli/commands/__init__.py
svg_text2path/cli/commands/compare.py
svg_text2path/cli/commands/convert.py
svg_text2path/cli/commands/deps.py
svg_text2path/cli/commands/fonts.py
svg_text2path/cli/commands/batch/__init__.py
svg_text2path/cli/commands/batch/compare.py
svg_text2path/cli/commands/batch/config.py
svg_text2path/cli/commands/batch/convert.py
svg_text2path/cli/commands/batch/regression.py
svg_text2path/cli/commands/batch/template.py
svg_text2path/cli/commands/batch/validation.py
svg_text2path/cli/config/__init__.py
svg_text2path/cli/config/defaults.py
svg_text2path/cli/config/yaml_config.py
svg_text2path/cli/utils/__init__.py
svg_text2path/cli/utils/banner.py
svg_text2path/cli/utils/output.py
svg_text2path/cli/utils/tools.py
svg_text2path/fonts/__init__.py
svg_text2path/fonts/cache.py
svg_text2path/fonts/downloader.py
svg_text2path/formats/__init__.py
svg_text2path/formats/base.py
svg_text2path/formats/css.py
svg_text2path/formats/epub.py
svg_text2path/formats/file.py
svg_text2path/formats/html.py
svg_text2path/formats/inkscape.py
svg_text2path/formats/javascript_code.py
svg_text2path/formats/json_csv.py
svg_text2path/formats/markdown.py
svg_text2path/formats/plaintext.py
svg_text2path/formats/python_code.py
svg_text2path/formats/registry.py
svg_text2path/formats/remote.py
svg_text2path/formats/rst.py
svg_text2path/formats/string.py
svg_text2path/formats/tree.py
svg_text2path/paths/__init__.py
svg_text2path/paths/generator.py
svg_text2path/paths/transform.py
svg_text2path/shaping/__init__.py
svg_text2path/shaping/bidi.py
svg_text2path/shaping/harfbuzz.py
svg_text2path/svg/__init__.py
svg_text2path/svg/parser.py
svg_text2path/tools/__init__.py
svg_text2path/tools/dependencies.py
svg_text2path/tools/external.py
svg_text2path/tools/installer.py
svg_text2path-0.5.0.dist-info/METADATA
svg_text2path-0.5.0.dist-info/WHEEL
svg_text2path-0.5.0.dist-info/entry_points.txt
svg_text2path-0.5.0.dist-info/licenses/LICENSE
svg_text2path-0.5.0.dist-info/RECORD
