Metadata-Version: 2.4
Name: svg-text2path
Version: 0.5.0
Summary: Convert SVG text elements to path outlines with HarfBuzz shaping
Project-URL: Homepage, https://github.com/Emasoft/svg-text2path
Project-URL: Documentation, https://github.com/Emasoft/svg-text2path#readme
Project-URL: Repository, https://github.com/Emasoft/svg-text2path.git
Project-URL: Issues, https://github.com/Emasoft/svg-text2path/issues
Project-URL: Changelog, https://github.com/Emasoft/svg-text2path/blob/main/CHANGELOG.md
Author-email: Emasoft <713559+Emasoft@users.noreply.github.com>
License: MIT
License-File: LICENSE
Keywords: convert,font,harfbuzz,path,svg,text,vector
Classifier: Development Status :: 4 - Beta
Classifier: Intended Audience :: Developers
Classifier: License :: OSI Approved :: MIT License
Classifier: Programming Language :: Python :: 3.11
Classifier: Programming Language :: Python :: 3.12
Classifier: Topic :: Multimedia :: Graphics :: Graphics Conversion
Classifier: Topic :: Text Processing :: Markup :: XML
Requires-Python: >=3.11
Requires-Dist: click>=8.0
Requires-Dist: defusedxml>=0.7.1
Requires-Dist: fonttools>=4.60.1
Requires-Dist: numpy>=2.2.6
Requires-Dist: pillow>=12.0.0
Requires-Dist: python-bidi>=0.6.7
Requires-Dist: pyyaml>=6.0
Requires-Dist: rich>=13.0
Requires-Dist: svg-path>=7.0
Requires-Dist: uharfbuzz>=0.52.0
Provides-Extra: bs4
Requires-Dist: beautifulsoup4>=4.12; extra == 'bs4'
Provides-Extra: dev
Requires-Dist: mypy>=1.8.0; extra == 'dev'
Requires-Dist: pytest-cov>=4.0; extra == 'dev'
Requires-Dist: pytest>=9.0.1; extra == 'dev'
Requires-Dist: ruff>=0.3.0; extra == 'dev'
Provides-Extra: lxml
Requires-Dist: lxml>=5.0; extra == 'lxml'
